listwizard/__init__.py
listwizard/listwizard.py
listwizard-0.1.1.dist-info/LICENSE
listwizard-0.1.1.dist-info/METADATA
listwizard-0.1.1.dist-info/WHEEL
listwizard-0.1.1.dist-info/top_level.txt
listwizard-0.1.1.dist-info/RECORD
