Metadata-Version: 2.1
Name: listwizard
Version: 0.1.1
Summary: Python biblioteka za analiziranje i manipuliranje listama.
Home-page: https://github.com/yourusername/listwizard
Author: o_Frun
Author-email: fran.cesljas@skole.hr
Classifier: Programming Language :: Python :: 3
Classifier: License :: OSI Approved :: MIT License
Classifier: Operating System :: OS Independent
Requires-Python: >=3.6
License-File: LICENSE
